{
  "id": "aai%2Fmodel-loader~master~I19e16b7447f5ef8b7533449b18895c2bc98188d2",
  "change_id": "I19e16b7447f5ef8b7533449b18895c2bc98188d2",
  "_number": 75566,
  "status": "MERGED",
  "timestamps": {
    "created": "2019-01-09 15:44:59.000000000",
    "updated": "2019-01-09 19:37:51.000000000",
    "submitted": "2019-01-09 19:32:48.000000000"
  },
  "accounts": {
    "owner": {
      "account_id": 4944,
      "name": "Stela Stoykova",
      "display_name": null,
      "email": "Stela.Stoykova@amdocs.com",
      "username": "sstoykov"
    },
    "submitter": {
      "account_id": 453,
      "name": "Steven Blimkie",
      "display_name": null,
      "email": "steven.blimkie@amdocs.com",
      "username": "sblimkie"
    }
  },
  "subject": "Added echo service to model-loader",
  "commit_message": "Added echo service to model-loader\n\nIssue-ID: AAI-2060\n\nChange-Id: I19e16b7447f5ef8b7533449b18895c2bc98188d2\nSigned-off-by: Stela Stoykova <Stela.Stoykova@amdocs.com>\n",
  "change_log": {
    "entry_count": 9,
    "entries": [
      {
        "id": "639b865926c592bc6af065a75b998e94e316a84a",
        "author": {
          "account_id": 4944,
          "name": "Stela Stoykova",
          "display_name": null,
          "email": "Stela.Stoykova@amdocs.com",
          "username": "sstoykov"
        },
        "author_role": "OWNER",
        "timestamp": "2019-01-09 15:44:59.000000000",
        "message": "Uploaded patch set 1.",
        "patchset_number": 1
      },
      {
        "id": "1513e9ae1c62a8352f344d8fa6c942820be01801",
        "author": {
          "account_id": 459,
          "name": "ONAP Jobbuilder",
          "display_name": null,
          "email": "onap-jobbuilder@jenkins.onap.org",
          "username": "onap-jobbuilder"
        },
        "author_role": "REVIEWER",
        "timestamp": "2019-01-09 15:48:59.000000000",
        "message": "Patch Set 1:\n\nBuild Started https://jenkins.onap.org/job/aai-model-loader-master-verify-java/119/",
        "patchset_number": 1
      },
      {
        "id": "2f612eac8578e9f187cec6ce5986de7bc72c25f5",
        "author": {
          "account_id": 459,
          "name": "ONAP Jobbuilder",
          "display_name": null,
          "email": "onap-jobbuilder@jenkins.onap.org",
          "username": "onap-jobbuilder"
        },
        "author_role": "REVIEWER",
        "timestamp": "2019-01-09 15:51:49.000000000",
        "message": "Patch Set 1: Verified+1\n\nBuild Successful \n\nhttps://jenkins.onap.org/job/aai-model-loader-master-verify-java/119/ : SUCCESS\n\nLogs: https://logs.onap.org/production/vex-yul-ecomp-jenkins-1/aai-model-loader-master-verify-java/119",
        "patchset_number": 1
      },
      {
        "id": "99ea4a89759295ea1b13ae31dc85a557e27cd772",
        "author": {
          "account_id": 931,
          "name": "Daniel Silverthorn",
          "display_name": null,
          "email": "daniel.silverthorn@amdocs.com",
          "username": "daniesilamdocs"
        },
        "author_role": "REVIEWER",
        "timestamp": "2019-01-09 18:28:08.000000000",
        "message": "Patch Set 1: Code-Review+1",
        "patchset_number": 1
      },
      {
        "id": "79745b844f9255504c6da08b72eaf2d7edbc2bc7",
        "author": {
          "account_id": 3597,
          "name": "Serban Popescu",
          "display_name": null,
          "email": "serban.popescu@amdocs.com",
          "username": "spopescu"
        },
        "author_role": "REVIEWER",
        "timestamp": "2019-01-09 19:00:09.000000000",
        "message": "Patch Set 1: Code-Review+1",
        "patchset_number": 1
      },
      {
        "id": "22730563f1d4bb649d08d76ac3eda0fe2d66e2c4",
        "author": {
          "account_id": 453,
          "name": "Steven Blimkie",
          "display_name": null,
          "email": "steven.blimkie@amdocs.com",
          "username": "sblimkie"
        },
        "author_role": "REVIEWER",
        "timestamp": "2019-01-09 19:32:43.000000000",
        "message": "Patch Set 1: Code-Review+2",
        "patchset_number": 1
      },
      {
        "id": "d89a647fe4d422cf499b4e38421d0c6d4a560be7",
        "author": null,
        "author_role": "UNKNOWN",
        "timestamp": "2019-01-09 19:32:48.000000000",
        "message": "Change has been successfully merged by Steven Blimkie",
        "patchset_number": 1
      },
      {
        "id": "05982e2d27704c7a84ba01e3923558ff1faf4841",
        "author": {
          "account_id": 459,
          "name": "ONAP Jobbuilder",
          "display_name": null,
          "email": "onap-jobbuilder@jenkins.onap.org",
          "username": "onap-jobbuilder"
        },
        "author_role": "REVIEWER",
        "timestamp": "2019-01-09 19:34:29.000000000",
        "message": "Patch Set 1:\n\nBuild Started https://jenkins.onap.org/job/aai-model-loader-master-merge-java/89/",
        "patchset_number": 1
      },
      {
        "id": "1a8e08e4f2e75ba55e839d9e10e7d11fbb6b1f92",
        "author": {
          "account_id": 459,
          "name": "ONAP Jobbuilder",
          "display_name": null,
          "email": "onap-jobbuilder@jenkins.onap.org",
          "username": "onap-jobbuilder"
        },
        "author_role": "REVIEWER",
        "timestamp": "2019-01-09 19:37:51.000000000",
        "message": "Patch Set 1:\n\nBuild Successful \n\nhttps://jenkins.onap.org/job/aai-model-loader-master-merge-java/89/ : SUCCESS\n\nLogs: https://logs.onap.org/production/vex-yul-ecomp-jenkins-1/aai-model-loader-master-merge-java/89",
        "patchset_number": 1
      }
    ]
  }
}