{
  "id": "vid~master~Icfe469b538c3dd5f82f95617ebbd6093b9e451dc",
  "change_id": "Icfe469b538c3dd5f82f95617ebbd6093b9e451dc",
  "_number": 99902,
  "status": "MERGED",
  "timestamps": {
    "created": "2019-12-24 19:29:41.000000000",
    "updated": "2019-12-25 03:17:36.000000000",
    "submitted": "2019-12-25 02:56:31.000000000"
  },
  "accounts": {
    "owner": {
      "account_id": 5673,
      "name": "Alexey Sandler",
      "display_name": null,
      "email": "alexey.sandler@intl.att.com",
      "username": "AlexeSandler"
    },
    "submitter": {
      "account_id": 4379,
      "name": "Ittay Stern",
      "display_name": null,
      "email": "ittay.stern@att.com",
      "username": "ittays"
    }
  },
  "subject": "Convert template summary from json to string.",
  "commit_message": "Convert template summary from json to string.\n\nIssue-ID: VID-724\nSigned-off-by: Alexey Sandler <alexey.sandler@intl.att.com>\nChange-Id: Icfe469b538c3dd5f82f95617ebbd6093b9e451dc\nSigned-off-by: Alexey Sandler <alexey.sandler@intl.att.com>\n",
  "change_log": {
    "entry_count": 11,
    "entries": [
      {
        "id": "7a438f352c96b9ed587df5fd1d8f3685d2a94e2e",
        "author": {
          "account_id": 5673,
          "name": "Alexey Sandler",
          "display_name": null,
          "email": "alexey.sandler@intl.att.com",
          "username": "AlexeSandler"
        },
        "author_role": "CI_BOT",
        "timestamp": "2019-12-24 19:29:41.000000000",
        "message": "Uploaded patch set 1.",
        "patchset_number": 1
      },
      {
        "id": "42f36daf2320a7178f87dbd8ea29475cf389d708",
        "author": {
          "account_id": 459,
          "name": "ONAP Jobbuilder",
          "display_name": null,
          "email": "onap-jobbuilder@jenkins.onap.org",
          "username": "onap-jobbuilder"
        },
        "author_role": "REVIEWER",
        "timestamp": "2019-12-24 19:32:15.000000000",
        "message": "Patch Set 1:\n\nBuild Started https://jenkins.onap.org/job/vid-master-verify-java/2083/",
        "patchset_number": 1
      },
      {
        "id": "ce3f9412d18d74ad3d5a1932f241c0fea50273c1",
        "author": {
          "account_id": 459,
          "name": "ONAP Jobbuilder",
          "display_name": null,
          "email": "onap-jobbuilder@jenkins.onap.org",
          "username": "onap-jobbuilder"
        },
        "author_role": "REVIEWER",
        "timestamp": "2019-12-24 19:48:26.000000000",
        "message": "Patch Set 1: Verified+1\n\nBuild Successful \n\nhttps://jenkins.onap.org/job/vid-master-verify-java/2083/ : SUCCESS\n\nLogs: https://logs.onap.org/production/vex-yul-ecomp-jenkins-1/vid-master-verify-java/2083",
        "patchset_number": 1
      },
      {
        "id": "203680c5396e83bbd161dd1944bfcaf807fed5fd",
        "author": {
          "account_id": 5673,
          "name": "Alexey Sandler",
          "display_name": null,
          "email": "alexey.sandler@intl.att.com",
          "username": "AlexeSandler"
        },
        "author_role": "CI_BOT",
        "timestamp": "2019-12-24 19:51:52.000000000",
        "message": "Uploaded patch set 2.",
        "patchset_number": 2
      },
      {
        "id": "5075627fe575d18390662886e02f27931a579ace",
        "author": {
          "account_id": 459,
          "name": "ONAP Jobbuilder",
          "display_name": null,
          "email": "onap-jobbuilder@jenkins.onap.org",
          "username": "onap-jobbuilder"
        },
        "author_role": "REVIEWER",
        "timestamp": "2019-12-24 19:54:17.000000000",
        "message": "Patch Set 2:\n\nBuild Started https://jenkins.onap.org/job/vid-master-verify-java/2084/",
        "patchset_number": 2
      },
      {
        "id": "9a02da2bb07730c7273ce7b35056de049c260576",
        "author": {
          "account_id": 459,
          "name": "ONAP Jobbuilder",
          "display_name": null,
          "email": "onap-jobbuilder@jenkins.onap.org",
          "username": "onap-jobbuilder"
        },
        "author_role": "REVIEWER",
        "timestamp": "2019-12-24 20:12:02.000000000",
        "message": "Patch Set 2: Verified+1\n\nBuild Successful \n\nhttps://jenkins.onap.org/job/vid-master-verify-java/2084/ : SUCCESS\n\nLogs: https://logs.onap.org/production/vex-yul-ecomp-jenkins-1/vid-master-verify-java/2084",
        "patchset_number": 2
      },
      {
        "id": "f81944e6688525b4e7ea9194824443fe1b60eaaf",
        "author": {
          "account_id": 4379,
          "name": "Ittay Stern",
          "display_name": null,
          "email": "ittay.stern@att.com",
          "username": "ittays"
        },
        "author_role": "CI_BOT",
        "timestamp": "2019-12-25 02:55:27.000000000",
        "message": "Removed Verified+1 by ONAP Jobbuilder <onap-jobbuilder@jenkins.onap.org>\n",
        "patchset_number": 2
      },
      {
        "id": "8ff74682fd6f09e52e6e7f7dc18ed281cf08222f",
        "author": {
          "account_id": 4379,
          "name": "Ittay Stern",
          "display_name": null,
          "email": "ittay.stern@att.com",
          "username": "ittays"
        },
        "author_role": "REVIEWER",
        "timestamp": "2019-12-25 02:56:12.000000000",
        "message": "Patch Set 2: Verified+1 Code-Review+2",
        "patchset_number": 2
      },
      {
        "id": "19e22c9bbd7b19ffe64defff7678618269edef35",
        "author": {
          "account_id": 4379,
          "name": "Ittay Stern",
          "display_name": null,
          "email": "ittay.stern@att.com",
          "username": "ittays"
        },
        "author_role": "CI_BOT",
        "timestamp": "2019-12-25 02:56:31.000000000",
        "message": "Change has been successfully merged by Ittay Stern",
        "patchset_number": 2
      },
      {
        "id": "c5865a4dd97cd77e4babcdef520d2fdc22420d62",
        "author": {
          "account_id": 459,
          "name": "ONAP Jobbuilder",
          "display_name": null,
          "email": "onap-jobbuilder@jenkins.onap.org",
          "username": "onap-jobbuilder"
        },
        "author_role": "REVIEWER",
        "timestamp": "2019-12-25 02:58:50.000000000",
        "message": "Patch Set 2:\n\nBuild Started https://jenkins.onap.org/job/vid-master-merge-java/896/",
        "patchset_number": 2
      },
      {
        "id": "02a8b6ef3686a92fc1eaebff8bc9c336185fc766",
        "author": {
          "account_id": 459,
          "name": "ONAP Jobbuilder",
          "display_name": null,
          "email": "onap-jobbuilder@jenkins.onap.org",
          "username": "onap-jobbuilder"
        },
        "author_role": "REVIEWER",
        "timestamp": "2019-12-25 03:17:36.000000000",
        "message": "Patch Set 2:\n\nBuild Successful \n\nhttps://jenkins.onap.org/job/vid-master-merge-java/896/ : SUCCESS\n\nLogs: https://logs.onap.org/production/vex-yul-ecomp-jenkins-1/vid-master-merge-java/896",
        "patchset_number": 2
      }
    ]
  }
}