{
  "id": "policy%2Fmodels~master~I9a0c59ac40fcfe7028c55bc285006545d989c683",
  "change_id": "I9a0c59ac40fcfe7028c55bc285006545d989c683",
  "_number": 87880,
  "status": "MERGED",
  "timestamps": {
    "created": "2019-05-16 14:08:58.000000000",
    "updated": "2019-05-16 14:29:39.000000000",
    "submitted": "2019-05-16 14:17:28.000000000"
  },
  "accounts": {
    "owner": {
      "account_id": 1943,
      "name": "Vidyashree Rama",
      "display_name": null,
      "email": "vidyashree.rama@huawei.com",
      "username": "Vidyashree-Huawei"
    },
    "submitter": {
      "account_id": 57,
      "name": "Pamela Dragosh",
      "display_name": null,
      "email": "pd1248@att.com",
      "username": "pdragosh"
    }
  },
  "subject": "Vf module info is not present in SDNC request",
  "commit_message": "Vf module info is not present in SDNC request\n\nVf module info is not present in SDNC request\n\nChange-Id: I9a0c59ac40fcfe7028c55bc285006545d989c683\nIssue-ID: POLICY-1774\nSigned-off-by: Vidyashree Rama <vidyashree.rama@huawei.com>\n",
  "change_log": {
    "entry_count": 6,
    "entries": [
      {
        "id": "ae13884428b55cb153c810d8fe965be4faecf32f",
        "author": {
          "account_id": 1943,
          "name": "Vidyashree Rama",
          "display_name": null,
          "email": "vidyashree.rama@huawei.com",
          "username": "Vidyashree-Huawei"
        },
        "author_role": "CI_BOT",
        "timestamp": "2019-05-16 14:08:58.000000000",
        "message": "Uploaded patch set 1.",
        "patchset_number": 1
      },
      {
        "id": "1edfd3199ecf60f96e70c5cdd9bae115ee492291",
        "author": {
          "account_id": 459,
          "name": "ONAP Jobbuilder",
          "display_name": null,
          "email": "onap-jobbuilder@jenkins.onap.org",
          "username": "onap-jobbuilder"
        },
        "author_role": "REVIEWER",
        "timestamp": "2019-05-16 14:11:21.000000000",
        "message": "Patch Set 1:\n\nBuild Started https://jenkins.onap.org/job/policy-models-master-verify-java/337/",
        "patchset_number": 1
      },
      {
        "id": "50a407cb348bc16410326b5d44995bad57722095",
        "author": {
          "account_id": 459,
          "name": "ONAP Jobbuilder",
          "display_name": null,
          "email": "onap-jobbuilder@jenkins.onap.org",
          "username": "onap-jobbuilder"
        },
        "author_role": "REVIEWER",
        "timestamp": "2019-05-16 14:16:05.000000000",
        "message": "Patch Set 1: Verified+1\n\nBuild Successful \n\nhttps://jenkins.onap.org/job/policy-models-master-verify-java/337/ : SUCCESS\n\nLogs: https://logs.onap.org/production/vex-yul-ecomp-jenkins-1/policy-models-master-verify-java/337",
        "patchset_number": 1
      },
      {
        "id": "185948975f16a0b08714dfa35ace71831a018540",
        "author": {
          "account_id": 57,
          "name": "Pamela Dragosh",
          "display_name": null,
          "email": "pd1248@att.com",
          "username": "pdragosh"
        },
        "author_role": "REVIEWER",
        "timestamp": "2019-05-16 14:17:22.000000000",
        "message": "Patch Set 1: Code-Review+2",
        "patchset_number": 1
      },
      {
        "id": "cd7877142db9c06a733dded79ec883d018b427f9",
        "author": {
          "account_id": 57,
          "name": "Pamela Dragosh",
          "display_name": null,
          "email": "pd1248@att.com",
          "username": "pdragosh"
        },
        "author_role": "CI_BOT",
        "timestamp": "2019-05-16 14:17:28.000000000",
        "message": "Change has been successfully merged by Pamela Dragosh",
        "patchset_number": 1
      },
      {
        "id": "9b81f00ed5cb98d2291578af8b89e199f9f0f156",
        "author": {
          "account_id": 459,
          "name": "ONAP Jobbuilder",
          "display_name": null,
          "email": "onap-jobbuilder@jenkins.onap.org",
          "username": "onap-jobbuilder"
        },
        "author_role": "REVIEWER",
        "timestamp": "2019-05-16 14:29:39.000000000",
        "message": "Patch Set 1:\n\nBuild Successful \n\nhttps://jenkins.onap.org/job/policy-models-master-merge-java/150/ : SUCCESS\n\nLogs: https://logs.onap.org/production/vex-yul-ecomp-jenkins-1/policy-models-master-merge-java/150",
        "patchset_number": 1
      }
    ]
  }
}