{
  "id": "cps~master~I9c4500727640040593aacbd209c2d5ec6a86a315",
  "change_id": "I9c4500727640040593aacbd209c2d5ec6a86a315",
  "_number": 137793,
  "status": "MERGED",
  "timestamps": {
    "created": "2024-04-26 11:01:27.000000000",
    "updated": "2024-04-30 15:37:51.000000000",
    "submitted": "2024-04-30 15:26:50.000000000"
  },
  "accounts": {
    "owner": {
      "account_id": 6742,
      "name": "Daniel Hanrahan",
      "display_name": null,
      "email": "daniel.hanrahan@est.tech",
      "username": "danielhanrahan"
    },
    "submitter": {
      "account_id": 7965,
      "name": "Priyank Maheshwari",
      "display_name": null,
      "email": "priyank.maheshwari@est.tech",
      "username": "mpriyank"
    }
  },
  "subject": "Release notes update for 3.4.8",
  "commit_message": "Release notes update for 3.4.8\n\nAdd release notes updates for bug fix CPS-2190 (slow module search)\n\nIssue-ID: CPS-2190\nSigned-off-by: danielhanrahan <daniel.hanrahan@est.tech>\nChange-Id: I9c4500727640040593aacbd209c2d5ec6a86a315\n",
  "change_log": {
    "entry_count": 43,
    "entries": [
      {
        "id": "a605d100b3e9a3f7867788e0dfeb8949e26b3a54",
        "author": {
          "account_id": 6742,
          "name": "Daniel Hanrahan",
          "display_name": null,
          "email": "daniel.hanrahan@est.tech",
          "username": "danielhanrahan"
        },
        "author_role": "CI_BOT",
        "timestamp": "2024-04-26 11:01:27.000000000",
        "message": "Uploaded patch set 1.",
        "patchset_number": 1
      },
      {
        "id": "224cc9ae4270a8d7e4bc8d0426a695995aab63f8",
        "author": {
          "account_id": 8351,
          "name": "ONAP Required GHA",
          "display_name": null,
          "email": "releng+onap.required.gha@linuxfoundation.org",
          "username": "onap.required.gha"
        },
        "author_role": "CI_BOT",
        "timestamp": "2024-04-26 11:01:40.000000000",
        "message": "Patch Set 1:\n\nSTARTED: https://github.com/onap/.github/actions/runs/8847236514",
        "patchset_number": 1
      },
      {
        "id": "13d727b0e7dc5d38003ec871b66bd413ff9f41ee",
        "author": {
          "account_id": 459,
          "name": "ONAP Jobbuilder",
          "display_name": null,
          "email": "onap-jobbuilder@jenkins.onap.org",
          "username": "onap-jobbuilder"
        },
        "author_role": "REVIEWER",
        "timestamp": "2024-04-26 11:02:22.000000000",
        "message": "Patch Set 1:\n\nBuild Started https://jenkins.onap.org/job/cps-sonar-verify/5660/ (1/3)",
        "patchset_number": 1
      },
      {
        "id": "436c90a237c25ccd93ce2233c6f3c466b441eda3",
        "author": {
          "account_id": 459,
          "name": "ONAP Jobbuilder",
          "display_name": null,
          "email": "onap-jobbuilder@jenkins.onap.org",
          "username": "onap-jobbuilder"
        },
        "author_role": "REVIEWER",
        "timestamp": "2024-04-26 11:02:55.000000000",
        "message": "Patch Set 1:\n\nBuild Started https://jenkins.onap.org/job/cps-master-verify-java/7316/ (2/3)",
        "patchset_number": 1
      },
      {
        "id": "a251a636f20a877a2b0321699ee1812cde318e3f",
        "author": {
          "account_id": 459,
          "name": "ONAP Jobbuilder",
          "display_name": null,
          "email": "onap-jobbuilder@jenkins.onap.org",
          "username": "onap-jobbuilder"
        },
        "author_role": "REVIEWER",
        "timestamp": "2024-04-26 11:03:20.000000000",
        "message": "Patch Set 1:\n\nBuild Started https://jenkins.onap.org/job/cps-review-verification-maven-master/6642/ (3/3)",
        "patchset_number": 1
      },
      {
        "id": "3ef7bf771780e7f48320c6fcbc542409941a4aad",
        "author": {
          "account_id": 8351,
          "name": "ONAP Required GHA",
          "display_name": null,
          "email": "releng+onap.required.gha@linuxfoundation.org",
          "username": "onap.required.gha"
        },
        "author_role": "CI_BOT",
        "timestamp": "2024-04-26 11:03:25.000000000",
        "message": "Patch Set 1: Verified+1\n\nSUCCESS: https://github.com/onap/.github/actions/runs/8847236514",
        "patchset_number": 1
      },
      {
        "id": "ff4e8fc8f9be7dd8531c6e932ab01135c8a2c61e",
        "author": {
          "account_id": 7965,
          "name": "Priyank Maheshwari",
          "display_name": null,
          "email": "priyank.maheshwari@est.tech",
          "username": "mpriyank"
        },
        "author_role": "REVIEWER",
        "timestamp": "2024-04-26 11:08:54.000000000",
        "message": "Patch Set 1: Code-Review+1",
        "patchset_number": 1
      },
      {
        "id": "50ecfdfde8f61bbac2124b072b65f6456c46a82f",
        "author": {
          "account_id": 459,
          "name": "ONAP Jobbuilder",
          "display_name": null,
          "email": "onap-jobbuilder@jenkins.onap.org",
          "username": "onap-jobbuilder"
        },
        "author_role": "REVIEWER",
        "timestamp": "2024-04-26 11:12:39.000000000",
        "message": "Patch Set 1: Verified+1\n\nBuild Successful \n\nhttps://jenkins.onap.org/job/cps-sonar-verify/5660/ : SUCCESS\n\nLogs: https://logs.onap.org/production/vex-yul-ecomp-jenkins-1/cps-sonar-verify/5660\n\nhttps://jenkins.onap.org/job/cps-review-verification-maven-master/6642/ : SUCCESS\n\nLogs: https://logs.onap.org/production/vex-yul-ecomp-jenkins-1/cps-review-verification-maven-master/6642\n\nhttps://jenkins.onap.org/job/cps-master-verify-java/7316/ : SUCCESS\n\nLogs: https://logs.onap.org/production/vex-yul-ecomp-jenkins-1/cps-master-verify-java/7316",
        "patchset_number": 1
      },
      {
        "id": "ce9a01829ae11f35d37e67f879e134b65ef934ef",
        "author": {
          "account_id": 6742,
          "name": "Daniel Hanrahan",
          "display_name": null,
          "email": "daniel.hanrahan@est.tech",
          "username": "danielhanrahan"
        },
        "author_role": "CI_BOT",
        "timestamp": "2024-04-29 12:46:24.000000000",
        "message": "Uploaded patch set 2.\n\nOutdated Votes:\n* Code-Review+1 (copy condition: \"changekind:NO_CHANGE OR changekind:TRIVIAL_REBASE OR is:MIN\")\n* Verified+1 (copy condition: \"changekind:NO_CHANGE\")\n",
        "patchset_number": 2
      },
      {
        "id": "7875e75e3abb1b8b315a306e7e03647cee9d0cd0",
        "author": {
          "account_id": 6742,
          "name": "Daniel Hanrahan",
          "display_name": null,
          "email": "daniel.hanrahan@est.tech",
          "username": "danielhanrahan"
        },
        "author_role": "CI_BOT",
        "timestamp": "2024-04-29 12:46:27.000000000",
        "message": "Topic release-notes removed",
        "patchset_number": 2
      },
      {
        "id": "d6facf9141e1c41caec8aa9122f86ed3111ec3dd",
        "author": {
          "account_id": 8351,
          "name": "ONAP Required GHA",
          "display_name": null,
          "email": "releng+onap.required.gha@linuxfoundation.org",
          "username": "onap.required.gha"
        },
        "author_role": "CI_BOT",
        "timestamp": "2024-04-29 12:46:37.000000000",
        "message": "Patch Set 2:\n\nSTARTED: https://github.com/onap/.github/actions/runs/8878801505",
        "patchset_number": 2
      },
      {
        "id": "b87cf7211e19b2540dea8c2c4d20a6caffcc1a09",
        "author": {
          "account_id": 459,
          "name": "ONAP Jobbuilder",
          "display_name": null,
          "email": "onap-jobbuilder@jenkins.onap.org",
          "username": "onap-jobbuilder"
        },
        "author_role": "REVIEWER",
        "timestamp": "2024-04-29 12:47:57.000000000",
        "message": "Patch Set 2:\n\nBuild Started https://jenkins.onap.org/job/cps-sonar-verify/5673/ (1/3)",
        "patchset_number": 2
      },
      {
        "id": "8fef37bce033da03abef07cc92a8bae07e81e734",
        "author": {
          "account_id": 459,
          "name": "ONAP Jobbuilder",
          "display_name": null,
          "email": "onap-jobbuilder@jenkins.onap.org",
          "username": "onap-jobbuilder"
        },
        "author_role": "REVIEWER",
        "timestamp": "2024-04-29 12:48:15.000000000",
        "message": "Patch Set 2:\n\nBuild Started https://jenkins.onap.org/job/cps-review-verification-maven-master/6655/ (2/3)",
        "patchset_number": 2
      },
      {
        "id": "b2c9f99f79491c5ddcfec1fc7e94866bb8835554",
        "author": {
          "account_id": 459,
          "name": "ONAP Jobbuilder",
          "display_name": null,
          "email": "onap-jobbuilder@jenkins.onap.org",
          "username": "onap-jobbuilder"
        },
        "author_role": "REVIEWER",
        "timestamp": "2024-04-29 12:48:27.000000000",
        "message": "Patch Set 2:\n\nBuild Started https://jenkins.onap.org/job/cps-master-verify-java/7329/ (3/3)",
        "patchset_number": 2
      },
      {
        "id": "cffbc9472f590c93980ab96cf5d7c6cfa9052d9e",
        "author": {
          "account_id": 8351,
          "name": "ONAP Required GHA",
          "display_name": null,
          "email": "releng+onap.required.gha@linuxfoundation.org",
          "username": "onap.required.gha"
        },
        "author_role": "CI_BOT",
        "timestamp": "2024-04-29 12:48:53.000000000",
        "message": "Patch Set 2: Verified+1\n\nSUCCESS: https://github.com/onap/.github/actions/runs/8878801505",
        "patchset_number": 2
      },
      {
        "id": "9e232a439eac691cfa6f41b9b418c965fdf6945c",
        "author": {
          "account_id": 459,
          "name": "ONAP Jobbuilder",
          "display_name": null,
          "email": "onap-jobbuilder@jenkins.onap.org",
          "username": "onap-jobbuilder"
        },
        "author_role": "REVIEWER",
        "timestamp": "2024-04-29 12:59:17.000000000",
        "message": "Patch Set 2: Verified+1\n\nBuild Successful \n\nhttps://jenkins.onap.org/job/cps-sonar-verify/5673/ : SUCCESS\n\nLogs: https://logs.onap.org/production/vex-yul-ecomp-jenkins-1/cps-sonar-verify/5673\n\nhttps://jenkins.onap.org/job/cps-review-verification-maven-master/6655/ : SUCCESS\n\nLogs: https://logs.onap.org/production/vex-yul-ecomp-jenkins-1/cps-review-verification-maven-master/6655\n\nhttps://jenkins.onap.org/job/cps-master-verify-java/7329/ : SUCCESS\n\nLogs: https://logs.onap.org/production/vex-yul-ecomp-jenkins-1/cps-master-verify-java/7329",
        "patchset_number": 2
      },
      {
        "id": "03ad944da6eb0e2b9ff18abe14a2142eb0df2ce9",
        "author": {
          "account_id": 7965,
          "name": "Priyank Maheshwari",
          "display_name": null,
          "email": "priyank.maheshwari@est.tech",
          "username": "mpriyank"
        },
        "author_role": "REVIEWER",
        "timestamp": "2024-04-29 14:22:33.000000000",
        "message": "Patch Set 2: Code-Review+1",
        "patchset_number": 2
      },
      {
        "id": "e38bb3e24502639f788f8d19a3aa12a84b6d431e",
        "author": {
          "account_id": 8063,
          "name": "Halil Cakal",
          "display_name": null,
          "email": "halil.cakal@est.tech",
          "username": "halil.cakal"
        },
        "author_role": "REVIEWER",
        "timestamp": "2024-04-29 15:40:16.000000000",
        "message": "Patch Set 2: Code-Review+1\n\n(1 comment)",
        "patchset_number": 2
      },
      {
        "id": "455b1c5ae75f03d0f7aff8fdad17cff0ed343c20",
        "author": {
          "account_id": 6742,
          "name": "Daniel Hanrahan",
          "display_name": null,
          "email": "daniel.hanrahan@est.tech",
          "username": "danielhanrahan"
        },
        "author_role": "OWNER",
        "timestamp": "2024-04-30 11:11:11.000000000",
        "message": "Patch Set 2: Code-Review-1\n\n(1 comment)",
        "patchset_number": 2
      },
      {
        "id": "c7a4433cc462b243d83efbfde0eaf25a45fe80fe",
        "author": {
          "account_id": 6742,
          "name": "Daniel Hanrahan",
          "display_name": null,
          "email": "daniel.hanrahan@est.tech",
          "username": "danielhanrahan"
        },
        "author_role": "CI_BOT",
        "timestamp": "2024-04-30 11:18:49.000000000",
        "message": "Uploaded patch set 3.\n\nOutdated Votes:\n* Code-Review+1, Code-Review-1 (copy condition: \"changekind:NO_CHANGE OR changekind:TRIVIAL_REBASE OR is:MIN\")\n* Verified+1 (copy condition: \"changekind:NO_CHANGE\")\n",
        "patchset_number": 3
      },
      {
        "id": "895ed115d370d50215ef0784cb2fa4042b4f3b1e",
        "author": {
          "account_id": 8351,
          "name": "ONAP Required GHA",
          "display_name": null,
          "email": "releng+onap.required.gha@linuxfoundation.org",
          "username": "onap.required.gha"
        },
        "author_role": "CI_BOT",
        "timestamp": "2024-04-30 11:19:03.000000000",
        "message": "Patch Set 3:\n\nSTARTED: https://github.com/onap/.github/actions/runs/8893859026",
        "patchset_number": 3
      },
      {
        "id": "d6d7b3d1e949ca766c57219350bd5b8d4eb4f506",
        "author": {
          "account_id": 6742,
          "name": "Daniel Hanrahan",
          "display_name": null,
          "email": "daniel.hanrahan@est.tech",
          "username": "danielhanrahan"
        },
        "author_role": "OWNER",
        "timestamp": "2024-04-30 11:19:30.000000000",
        "message": "Patch Set 3:\n\n(1 comment)",
        "patchset_number": 3
      },
      {
        "id": "0486524cc1265575286002ced196e6f912537312",
        "author": {
          "account_id": 459,
          "name": "ONAP Jobbuilder",
          "display_name": null,
          "email": "onap-jobbuilder@jenkins.onap.org",
          "username": "onap-jobbuilder"
        },
        "author_role": "REVIEWER",
        "timestamp": "2024-04-30 11:19:57.000000000",
        "message": "Patch Set 3:\n\nBuild Started https://jenkins.onap.org/job/cps-review-verification-maven-master/6673/ (1/3)",
        "patchset_number": 3
      },
      {
        "id": "09e574b3ebb7821450cd7f2b7096ecd06cd9c151",
        "author": {
          "account_id": 8351,
          "name": "ONAP Required GHA",
          "display_name": null,
          "email": "releng+onap.required.gha@linuxfoundation.org",
          "username": "onap.required.gha"
        },
        "author_role": "CI_BOT",
        "timestamp": "2024-04-30 11:20:51.000000000",
        "message": "Patch Set 3: Verified+1\n\nSUCCESS: https://github.com/onap/.github/actions/runs/8893859026",
        "patchset_number": 3
      },
      {
        "id": "761ed582c5d4370f2d22bf8cc2f98401e220b2bf",
        "author": {
          "account_id": 459,
          "name": "ONAP Jobbuilder",
          "display_name": null,
          "email": "onap-jobbuilder@jenkins.onap.org",
          "username": "onap-jobbuilder"
        },
        "author_role": "REVIEWER",
        "timestamp": "2024-04-30 11:21:47.000000000",
        "message": "Patch Set 3:\n\nBuild Started https://jenkins.onap.org/job/cps-sonar-verify/5690/ (2/3)",
        "patchset_number": 3
      },
      {
        "id": "4dc12913eb2c946bd4140db7e5dfc31277d760ed",
        "author": {
          "account_id": 459,
          "name": "ONAP Jobbuilder",
          "display_name": null,
          "email": "onap-jobbuilder@jenkins.onap.org",
          "username": "onap-jobbuilder"
        },
        "author_role": "REVIEWER",
        "timestamp": "2024-04-30 11:22:27.000000000",
        "message": "Patch Set 3:\n\nBuild Started https://jenkins.onap.org/job/cps-master-verify-java/7346/ (3/3)",
        "patchset_number": 3
      },
      {
        "id": "b70dce174a3ec52e07640772a3f964e3911ea5e3",
        "author": {
          "account_id": 459,
          "name": "ONAP Jobbuilder",
          "display_name": null,
          "email": "onap-jobbuilder@jenkins.onap.org",
          "username": "onap-jobbuilder"
        },
        "author_role": "REVIEWER",
        "timestamp": "2024-04-30 11:32:24.000000000",
        "message": "Patch Set 3: Verified+1\n\nBuild Successful \n\nhttps://jenkins.onap.org/job/cps-sonar-verify/5690/ : SUCCESS\n\nLogs: https://logs.onap.org/production/vex-yul-ecomp-jenkins-1/cps-sonar-verify/5690\n\nhttps://jenkins.onap.org/job/cps-review-verification-maven-master/6673/ : SUCCESS\n\nLogs: https://logs.onap.org/production/vex-yul-ecomp-jenkins-1/cps-review-verification-maven-master/6673\n\nhttps://jenkins.onap.org/job/cps-master-verify-java/7346/ : SUCCESS\n\nLogs: https://logs.onap.org/production/vex-yul-ecomp-jenkins-1/cps-master-verify-java/7346",
        "patchset_number": 3
      },
      {
        "id": "8517e489d2f5bf3d96597dd0fcd8f1d81764408a",
        "author": {
          "account_id": 8063,
          "name": "Halil Cakal",
          "display_name": null,
          "email": "halil.cakal@est.tech",
          "username": "halil.cakal"
        },
        "author_role": "REVIEWER",
        "timestamp": "2024-04-30 12:20:53.000000000",
        "message": "Patch Set 3: Code-Review+1",
        "patchset_number": 3
      },
      {
        "id": "0eaf81a79894152d9cd80b70102528112d915209",
        "author": {
          "account_id": 7931,
          "name": "Lee Anjella Macabuhay",
          "display_name": null,
          "email": "lee.anjella.macabuhay@est.tech",
          "username": "emaclee"
        },
        "author_role": "REVIEWER",
        "timestamp": "2024-04-30 12:24:09.000000000",
        "message": "Patch Set 3: Code-Review+1",
        "patchset_number": 3
      },
      {
        "id": "3f364e4b06ad86556501e28e0dc552739295e09c",
        "author": {
          "account_id": 4893,
          "name": "Gerard Nugent",
          "display_name": null,
          "email": "gerard.nugent@est.tech",
          "username": "egernug"
        },
        "author_role": "REVIEWER",
        "timestamp": "2024-04-30 12:39:08.000000000",
        "message": "Patch Set 3: Code-Review+1",
        "patchset_number": 3
      },
      {
        "id": "fde20c1261f9addc806035fd4e4b1c1fa1eacccd",
        "author": {
          "account_id": 6742,
          "name": "Daniel Hanrahan",
          "display_name": null,
          "email": "daniel.hanrahan@est.tech",
          "username": "danielhanrahan"
        },
        "author_role": "CI_BOT",
        "timestamp": "2024-04-30 15:01:37.000000000",
        "message": "Uploaded patch set 4.\n\nOutdated Votes:\n* Code-Review+1 (copy condition: \"changekind:NO_CHANGE OR changekind:TRIVIAL_REBASE OR is:MIN\")\n* Verified+1 (copy condition: \"changekind:NO_CHANGE\")\n",
        "patchset_number": 4
      },
      {
        "id": "eb7d5e8ea6dd44ea1d12ea65494792f428a24bdd",
        "author": {
          "account_id": 8351,
          "name": "ONAP Required GHA",
          "display_name": null,
          "email": "releng+onap.required.gha@linuxfoundation.org",
          "username": "onap.required.gha"
        },
        "author_role": "CI_BOT",
        "timestamp": "2024-04-30 15:01:51.000000000",
        "message": "Patch Set 4:\n\nSTARTED: https://github.com/onap/.github/actions/runs/8897068585",
        "patchset_number": 4
      },
      {
        "id": "47675bc281ce579359d6944b529390095e168af9",
        "author": {
          "account_id": 459,
          "name": "ONAP Jobbuilder",
          "display_name": null,
          "email": "onap-jobbuilder@jenkins.onap.org",
          "username": "onap-jobbuilder"
        },
        "author_role": "REVIEWER",
        "timestamp": "2024-04-30 15:03:24.000000000",
        "message": "Patch Set 4:\n\nBuild Started https://jenkins.onap.org/job/cps-sonar-verify/5698/ (1/3)",
        "patchset_number": 4
      },
      {
        "id": "583cc92e510490f7f1abefd2ea42ccd6e44e0c34",
        "author": {
          "account_id": 459,
          "name": "ONAP Jobbuilder",
          "display_name": null,
          "email": "onap-jobbuilder@jenkins.onap.org",
          "username": "onap-jobbuilder"
        },
        "author_role": "REVIEWER",
        "timestamp": "2024-04-30 15:03:49.000000000",
        "message": "Patch Set 4:\n\nBuild Started https://jenkins.onap.org/job/cps-review-verification-maven-master/6681/ (2/3)",
        "patchset_number": 4
      },
      {
        "id": "74e4c08ce2d2c5f9afd458e4653fc5d47b0aaa32",
        "author": {
          "account_id": 8351,
          "name": "ONAP Required GHA",
          "display_name": null,
          "email": "releng+onap.required.gha@linuxfoundation.org",
          "username": "onap.required.gha"
        },
        "author_role": "CI_BOT",
        "timestamp": "2024-04-30 15:03:54.000000000",
        "message": "Patch Set 4: Verified+1\n\nSUCCESS: https://github.com/onap/.github/actions/runs/8897068585",
        "patchset_number": 4
      },
      {
        "id": "ec79a672c035e0f739b0453c2f6c006a93dc7143",
        "author": {
          "account_id": 459,
          "name": "ONAP Jobbuilder",
          "display_name": null,
          "email": "onap-jobbuilder@jenkins.onap.org",
          "username": "onap-jobbuilder"
        },
        "author_role": "REVIEWER",
        "timestamp": "2024-04-30 15:04:19.000000000",
        "message": "Patch Set 4:\n\nBuild Started https://jenkins.onap.org/job/cps-master-verify-java/7354/ (3/3)",
        "patchset_number": 4
      },
      {
        "id": "56035b895047cbeaf051e79614cf8bef5fab8ca1",
        "author": {
          "account_id": 459,
          "name": "ONAP Jobbuilder",
          "display_name": null,
          "email": "onap-jobbuilder@jenkins.onap.org",
          "username": "onap-jobbuilder"
        },
        "author_role": "REVIEWER",
        "timestamp": "2024-04-30 15:14:17.000000000",
        "message": "Patch Set 4: Verified+1\n\nBuild Successful \n\nhttps://jenkins.onap.org/job/cps-sonar-verify/5698/ : SUCCESS\n\nLogs: https://logs.onap.org/production/vex-yul-ecomp-jenkins-1/cps-sonar-verify/5698\n\nhttps://jenkins.onap.org/job/cps-review-verification-maven-master/6681/ : SUCCESS\n\nLogs: https://logs.onap.org/production/vex-yul-ecomp-jenkins-1/cps-review-verification-maven-master/6681\n\nhttps://jenkins.onap.org/job/cps-master-verify-java/7354/ : SUCCESS\n\nLogs: https://logs.onap.org/production/vex-yul-ecomp-jenkins-1/cps-master-verify-java/7354",
        "patchset_number": 4
      },
      {
        "id": "7b9fab39d0204de3cef52c9c809c95384a058d8f",
        "author": {
          "account_id": 7965,
          "name": "Priyank Maheshwari",
          "display_name": null,
          "email": "priyank.maheshwari@est.tech",
          "username": "mpriyank"
        },
        "author_role": "REVIEWER",
        "timestamp": "2024-04-30 15:25:39.000000000",
        "message": "Patch Set 4: Code-Review+2",
        "patchset_number": 4
      },
      {
        "id": "7d9163af2d406f8925f9b2c4bcf4cda881976680",
        "author": {
          "account_id": 7965,
          "name": "Priyank Maheshwari",
          "display_name": null,
          "email": "priyank.maheshwari@est.tech",
          "username": "mpriyank"
        },
        "author_role": "REVIEWER",
        "timestamp": "2024-04-30 15:26:47.000000000",
        "message": "Patch Set 4:\n\n(1 comment)",
        "patchset_number": 4
      },
      {
        "id": "39d6b85299d2d5e56e6dd5fc6aebe6e5c18bc7b0",
        "author": {
          "account_id": 7965,
          "name": "Priyank Maheshwari",
          "display_name": null,
          "email": "priyank.maheshwari@est.tech",
          "username": "mpriyank"
        },
        "author_role": "CI_BOT",
        "timestamp": "2024-04-30 15:26:50.000000000",
        "message": "Change has been successfully merged",
        "patchset_number": 4
      },
      {
        "id": "fb484356a671f793b9703f94264c573c77689c4e",
        "author": {
          "account_id": 8351,
          "name": "ONAP Required GHA",
          "display_name": null,
          "email": "releng+onap.required.gha@linuxfoundation.org",
          "username": "onap.required.gha"
        },
        "author_role": "CI_BOT",
        "timestamp": "2024-04-30 15:27:03.000000000",
        "message": "Patch Set 1:\n\nSTARTED: https://github.com/onap/.github/actions/runs/8897477713",
        "patchset_number": 1
      },
      {
        "id": "1275f09823f4c719538d841510cd48b6ff25cc35",
        "author": {
          "account_id": 8351,
          "name": "ONAP Required GHA",
          "display_name": null,
          "email": "releng+onap.required.gha@linuxfoundation.org",
          "username": "onap.required.gha"
        },
        "author_role": "CI_BOT",
        "timestamp": "2024-04-30 15:29:23.000000000",
        "message": "Patch Set 1:\n\nSUCCESS: https://github.com/onap/.github/actions/runs/8897477713",
        "patchset_number": 1
      },
      {
        "id": "0f04610f9d940c374ac5c8139e70bb24f5e32094",
        "author": {
          "account_id": 459,
          "name": "ONAP Jobbuilder",
          "display_name": null,
          "email": "onap-jobbuilder@jenkins.onap.org",
          "username": "onap-jobbuilder"
        },
        "author_role": "REVIEWER",
        "timestamp": "2024-04-30 15:37:51.000000000",
        "message": "Patch Set 4:\n\nBuild Successful \n\nhttps://jenkins.onap.org/job/cps-master-merge-java/1313/ : SUCCESS\n\nLogs: https://logs.onap.org/production/vex-yul-ecomp-jenkins-1/cps-master-merge-java/1313\n\nhttps://jenkins.onap.org/job/cps-merge-verification-maven-master/1178/ : SUCCESS\n\nLogs: https://logs.onap.org/production/vex-yul-ecomp-jenkins-1/cps-merge-verification-maven-master/1178",
        "patchset_number": 4
      }
    ]
  }
}