{
  "id": "cps%2Fncmp-dmi-plugin~master~Id04a6f429399bd5a5dae723377be777c36fe0f24",
  "change_id": "Id04a6f429399bd5a5dae723377be777c36fe0f24",
  "_number": 144214,
  "status": "MERGED",
  "timestamps": {
    "created": "2026-05-05 09:31:43.000000000",
    "updated": "2026-05-05 12:47:04.000000000",
    "submitted": "2026-05-05 12:33:49.000000000"
  },
  "accounts": {
    "owner": {
      "account_id": 8171,
      "name": "Sean Beirne",
      "display_name": "Seán Beirne",
      "email": "sean.beirne@est.tech",
      "username": "seanbeirne"
    },
    "submitter": {
      "account_id": 4893,
      "name": "Gerard Nugent",
      "display_name": null,
      "email": "gerard.nugent@est.tech",
      "username": "egernug"
    }
  },
  "subject": "DMI release stage #5",
  "commit_message": "DMI release stage #5\n\nIssue-ID: CPS-3211\nChange-Id: Id04a6f429399bd5a5dae723377be777c36fe0f24\nSigned-off-by: seanbeirne <sean.beirne@est.tech>\n",
  "change_log": {
    "entry_count": 17,
    "entries": [
      {
        "id": "7c419ce68fbbf610a3fe8fa3ab2406f7e3e6fd71",
        "author": {
          "account_id": 8171,
          "name": "Sean Beirne",
          "display_name": "Seán Beirne",
          "email": "sean.beirne@est.tech",
          "username": "seanbeirne"
        },
        "author_role": "CI_BOT",
        "timestamp": "2026-05-05 09:31:43.000000000",
        "message": "Uploaded patch set 1.",
        "patchset_number": 1
      },
      {
        "id": "2f0340109d9b9c1f89ee640ab4d5057c58841ec7",
        "author": {
          "account_id": 8478,
          "name": "ONAP Bypass GHA",
          "display_name": null,
          "email": "releng+onap.bypass.gha@linuxfoundation.org",
          "username": "onap.bypass.gha"
        },
        "author_role": "CI_BOT",
        "timestamp": "2026-05-05 09:32:01.000000000",
        "message": "Patch Set 1:\n\nSTARTED: https://github.com/onap/.github/actions/runs/25368630803",
        "patchset_number": 1
      },
      {
        "id": "938ef4aba5a66d13b3017793c847094519874f25",
        "author": {
          "account_id": 8351,
          "name": "ONAP Required GHA",
          "display_name": null,
          "email": "releng+onap.required.gha@linuxfoundation.org",
          "username": "onap.required.gha"
        },
        "author_role": "CI_BOT",
        "timestamp": "2026-05-05 09:32:02.000000000",
        "message": "Patch Set 1:\n\nSTARTED: https://github.com/onap/.github/actions/runs/25368632328",
        "patchset_number": 1
      },
      {
        "id": "272cdc7bff4a5f531c8dd9a2074d32ab27596011",
        "author": {
          "account_id": 8351,
          "name": "ONAP Required GHA",
          "display_name": null,
          "email": "releng+onap.required.gha@linuxfoundation.org",
          "username": "onap.required.gha"
        },
        "author_role": "CI_BOT",
        "timestamp": "2026-05-05 09:32:45.000000000",
        "message": "Patch Set 1: Verified+1\n\nSUCCESS: https://github.com/onap/.github/actions/runs/25368632328",
        "patchset_number": 1
      },
      {
        "id": "74eabcfcec01a3958625e9563f09c9ff2c1157df",
        "author": {
          "account_id": 459,
          "name": "ONAP Jobbuilder",
          "display_name": null,
          "email": "onap-jobbuilder@jenkins.onap.org",
          "username": "onap-jobbuilder"
        },
        "author_role": "REVIEWER",
        "timestamp": "2026-05-05 09:33:06.000000000",
        "message": "Patch Set 1:\n\nBuild Started https://jenkins.onap.org/job/cps-ncmp-dmi-plugin-maven-docker-verify-master-mvn36-openjdk17/501/ (1/3)",
        "patchset_number": 1
      },
      {
        "id": "74c7d7e5b202098bac1ce3f39b843fae300718c2",
        "author": {
          "account_id": 459,
          "name": "ONAP Jobbuilder",
          "display_name": null,
          "email": "onap-jobbuilder@jenkins.onap.org",
          "username": "onap-jobbuilder"
        },
        "author_role": "REVIEWER",
        "timestamp": "2026-05-05 09:33:17.000000000",
        "message": "Patch Set 1:\n\nBuild Started https://jenkins.onap.org/job/cps-ncmp-dmi-plugin-sonar-verify/825/ (2/3)",
        "patchset_number": 1
      },
      {
        "id": "635595adebe5f8de1299148429c9a317a02ad2f1",
        "author": {
          "account_id": 459,
          "name": "ONAP Jobbuilder",
          "display_name": null,
          "email": "onap-jobbuilder@jenkins.onap.org",
          "username": "onap-jobbuilder"
        },
        "author_role": "REVIEWER",
        "timestamp": "2026-05-05 09:33:43.000000000",
        "message": "Patch Set 1:\n\nBuild Started https://jenkins.onap.org/job/cps-ncmp-dmi-plugin-release-verify-master/12/ (3/3)",
        "patchset_number": 1
      },
      {
        "id": "88a1afa0342011c6b57374f13b595ff1904143ee",
        "author": {
          "account_id": 8478,
          "name": "ONAP Bypass GHA",
          "display_name": null,
          "email": "releng+onap.bypass.gha@linuxfoundation.org",
          "username": "onap.bypass.gha"
        },
        "author_role": "CI_BOT",
        "timestamp": "2026-05-05 09:34:06.000000000",
        "message": "Patch Set 1: Verified-1\n\nFAILURE: https://github.com/onap/.github/actions/runs/25368630803",
        "patchset_number": 1
      },
      {
        "id": "53f8c3ba9420e95fbda46916429fea3100ad7be8",
        "author": {
          "account_id": 459,
          "name": "ONAP Jobbuilder",
          "display_name": null,
          "email": "onap-jobbuilder@jenkins.onap.org",
          "username": "onap-jobbuilder"
        },
        "author_role": "REVIEWER",
        "timestamp": "2026-05-05 09:38:33.000000000",
        "message": "Patch Set 1: Verified+1\n\nBuild Successful \n\nhttps://jenkins.onap.org/job/cps-ncmp-dmi-plugin-release-verify-master/12/ : SUCCESS\n\nLogs: https://logs.onap.org/production/vex-yul-ecomp-jenkins-1/cps-ncmp-dmi-plugin-release-verify-master/12\n\nhttps://jenkins.onap.org/job/cps-ncmp-dmi-plugin-maven-docker-verify-master-mvn36-openjdk17/501/ : SUCCESS\n\nLogs: https://logs.onap.org/production/vex-yul-ecomp-jenkins-1/cps-ncmp-dmi-plugin-maven-docker-verify-master-mvn36-openjdk17/501\n\nhttps://jenkins.onap.org/job/cps-ncmp-dmi-plugin-sonar-verify/825/ : SUCCESS\n\nLogs: https://logs.onap.org/production/vex-yul-ecomp-jenkins-1/cps-ncmp-dmi-plugin-sonar-verify/825",
        "patchset_number": 1
      },
      {
        "id": "ae0cb80bea78357b08318bca5eb665564b7394c4",
        "author": {
          "account_id": 4893,
          "name": "Gerard Nugent",
          "display_name": null,
          "email": "gerard.nugent@est.tech",
          "username": "egernug"
        },
        "author_role": "REVIEWER",
        "timestamp": "2026-05-05 09:55:01.000000000",
        "message": "Patch Set 1: Verified+1 Code-Review+2",
        "patchset_number": 1
      },
      {
        "id": "9ae3acda56b388724412e597caffcafe18e9d03c",
        "author": {
          "account_id": 4893,
          "name": "Gerard Nugent",
          "display_name": null,
          "email": "gerard.nugent@est.tech",
          "username": "egernug"
        },
        "author_role": "REVIEWER",
        "timestamp": "2026-05-05 09:55:09.000000000",
        "message": "Patch Set 1: Code-Review+1",
        "patchset_number": 1
      },
      {
        "id": "abc295db560ee90628edc6f9f62a6886a1031297",
        "author": {
          "account_id": 4893,
          "name": "Gerard Nugent",
          "display_name": null,
          "email": "gerard.nugent@est.tech",
          "username": "egernug"
        },
        "author_role": "REVIEWER",
        "timestamp": "2026-05-05 09:55:12.000000000",
        "message": "Patch Set 1: Code-Review+2",
        "patchset_number": 1
      },
      {
        "id": "594a7820517ba22dddb1205669bc106266731608",
        "author": {
          "account_id": 4893,
          "name": "Gerard Nugent",
          "display_name": null,
          "email": "gerard.nugent@est.tech",
          "username": "egernug"
        },
        "author_role": "CI_BOT",
        "timestamp": "2026-05-05 09:55:20.000000000",
        "message": "Removed Verified-1 by <GERRIT_ACCOUNT_8478>\n",
        "patchset_number": 1
      },
      {
        "id": "71cc00ed1cd803693e9b5a132e7a06d7e418aa12",
        "author": {
          "account_id": 4893,
          "name": "Gerard Nugent",
          "display_name": null,
          "email": "gerard.nugent@est.tech",
          "username": "egernug"
        },
        "author_role": "CI_BOT",
        "timestamp": "2026-05-05 12:33:49.000000000",
        "message": "Change has been successfully merged",
        "patchset_number": 1
      },
      {
        "id": "ba43c9ec69b10414c45dc7ba3d83ef7e2bab3c6d",
        "author": {
          "account_id": 8351,
          "name": "ONAP Required GHA",
          "display_name": null,
          "email": "releng+onap.required.gha@linuxfoundation.org",
          "username": "onap.required.gha"
        },
        "author_role": "CI_BOT",
        "timestamp": "2026-05-05 12:34:05.000000000",
        "message": "Patch Set 1:\n\nSTARTED: https://github.com/onap/.github/actions/runs/25376608238",
        "patchset_number": 1
      },
      {
        "id": "f5826447db2b4389567ef2ebb7ad0a23451b8a10",
        "author": {
          "account_id": 8351,
          "name": "ONAP Required GHA",
          "display_name": null,
          "email": "releng+onap.required.gha@linuxfoundation.org",
          "username": "onap.required.gha"
        },
        "author_role": "CI_BOT",
        "timestamp": "2026-05-05 12:36:22.000000000",
        "message": "Patch Set 1:\n\nSUCCESS: https://github.com/onap/.github/actions/runs/25376608238",
        "patchset_number": 1
      },
      {
        "id": "ad1e915e134fa87495cfbb32e18fa8eb6582ba38",
        "author": {
          "account_id": 459,
          "name": "ONAP Jobbuilder",
          "display_name": null,
          "email": "onap-jobbuilder@jenkins.onap.org",
          "username": "onap-jobbuilder"
        },
        "author_role": "REVIEWER",
        "timestamp": "2026-05-05 12:47:04.000000000",
        "message": "Patch Set 1:\n\nBuild Successful \n\nhttps://jenkins.onap.org/job/cps-ncmp-dmi-plugin-maven-merge-master/2131/ : SUCCESS\n\nLogs: https://logs.onap.org/production/vex-yul-ecomp-jenkins-1/cps-ncmp-dmi-plugin-maven-merge-master/2131\n\nhttps://jenkins.onap.org/job/cps-ncmp-dmi-plugin-release-merge-master/9/ : SUCCESS\n\nLogs: https://logs.onap.org/production/vex-yul-ecomp-jenkins-1/cps-ncmp-dmi-plugin-release-merge-master/9\n\nhttps://jenkins.onap.org/job/cps-ncmp-dmi-plugin-merge-verification-maven-master/234/ : SUCCESS\n\nLogs: https://logs.onap.org/production/vex-yul-ecomp-jenkins-1/cps-ncmp-dmi-plugin-merge-verification-maven-master/234",
        "patchset_number": 1
      }
    ]
  }
}