{
  "id": "optf%2Fosdf~master~Ib7620cb19850d77e80b2baea5ef318e8b0182d7c",
  "change_id": "Ib7620cb19850d77e80b2baea5ef318e8b0182d7c",
  "_number": 106885,
  "status": "MERGED",
  "timestamps": {
    "created": "2020-04-30 11:03:22.000000000",
    "updated": "2020-05-05 14:30:11.000000000",
    "submitted": "2020-05-05 14:08:34.000000000"
  },
  "accounts": {
    "owner": {
      "account_id": 2705,
      "name": "dhebeha mj",
      "display_name": null,
      "email": "dhebeha.mj71@wipro.com",
      "username": "dhebeha"
    },
    "submitter": {
      "account_id": 2923,
      "name": "Vikas Varma",
      "display_name": null,
      "email": "vikas.varma@att.com",
      "username": "vrvarma"
    }
  },
  "subject": "Change to support PCI unchangeable cells",
  "commit_message": "Change to support PCI unchangeable cells\n\nIssue-ID: OPTFRA-678\nSigned-off-by: dhebeha <dhebeha.mj71@wipro.com>\nChange-Id: Ib7620cb19850d77e80b2baea5ef318e8b0182d7c\n",
  "change_log": {
    "entry_count": 13,
    "entries": [
      {
        "id": "8b496e2d23b791ab0fd78812215a44f59996ebd4",
        "author": {
          "account_id": 2705,
          "name": "dhebeha mj",
          "display_name": null,
          "email": "dhebeha.mj71@wipro.com",
          "username": "dhebeha"
        },
        "author_role": "CI_BOT",
        "timestamp": "2020-04-30 11:03:22.000000000",
        "message": "Uploaded patch set 1.",
        "patchset_number": 1
      },
      {
        "id": "5b6d7a748aa7e23332794a81c74299a3e3c7821b",
        "author": {
          "account_id": 459,
          "name": "ONAP Jobbuilder",
          "display_name": null,
          "email": "onap-jobbuilder@jenkins.onap.org",
          "username": "onap-jobbuilder"
        },
        "author_role": "REVIEWER",
        "timestamp": "2020-04-30 11:06:18.000000000",
        "message": "Patch Set 1:\n\nBuild Started https://jenkins.onap.org/job/optf-osdf-master-osdf-verify-python/451/",
        "patchset_number": 1
      },
      {
        "id": "942a60f383f3e826417b8fe8107e335606069608",
        "author": {
          "account_id": 2705,
          "name": "dhebeha mj",
          "display_name": null,
          "email": "dhebeha.mj71@wipro.com",
          "username": "dhebeha"
        },
        "author_role": "CI_BOT",
        "timestamp": "2020-04-30 11:06:51.000000000",
        "message": "Uploaded patch set 2.",
        "patchset_number": 2
      },
      {
        "id": "2335bc0761b9b0e0b1b951e97406d0a97a20fae8",
        "author": {
          "account_id": 459,
          "name": "ONAP Jobbuilder",
          "display_name": null,
          "email": "onap-jobbuilder@jenkins.onap.org",
          "username": "onap-jobbuilder"
        },
        "author_role": "REVIEWER",
        "timestamp": "2020-04-30 11:09:05.000000000",
        "message": "Patch Set 1: Verified-1\n\nBuild Failed \n\nhttps://jenkins.onap.org/job/optf-osdf-master-osdf-verify-python/451/ : ABORTED\n\nNo problems were identified. If you know why this problem occurred, please add a suitable Cause for it. ( https://jenkins.onap.org/job/optf-osdf-master-osdf-verify-python/451/ )\n\nLogs: https://logs.onap.org/production/vex-yul-ecomp-jenkins-1/optf-osdf-master-osdf-verify-python/451",
        "patchset_number": 1
      },
      {
        "id": "ce0896a430bc80044b15142849b40124ed71797c",
        "author": {
          "account_id": 459,
          "name": "ONAP Jobbuilder",
          "display_name": null,
          "email": "onap-jobbuilder@jenkins.onap.org",
          "username": "onap-jobbuilder"
        },
        "author_role": "REVIEWER",
        "timestamp": "2020-04-30 11:09:48.000000000",
        "message": "Patch Set 2:\n\nBuild Started https://jenkins.onap.org/job/optf-osdf-master-osdf-verify-python/452/",
        "patchset_number": 2
      },
      {
        "id": "755546291236d117888f1971396ca6ae8fb96ea0",
        "author": {
          "account_id": 2671,
          "name": "krishna moorthy",
          "display_name": null,
          "email": "krishna981996@gmail.com",
          "username": "krishnaa96"
        },
        "author_role": "REVIEWER",
        "timestamp": "2020-04-30 11:10:24.000000000",
        "message": "Patch Set 2:\n\nrecheck",
        "patchset_number": 2
      },
      {
        "id": "1e5056dbb021252325865eece1023f07266fa645",
        "author": {
          "account_id": 459,
          "name": "ONAP Jobbuilder",
          "display_name": null,
          "email": "onap-jobbuilder@jenkins.onap.org",
          "username": "onap-jobbuilder"
        },
        "author_role": "REVIEWER",
        "timestamp": "2020-04-30 11:13:06.000000000",
        "message": "Patch Set 2:\n\nBuild Started https://jenkins.onap.org/job/optf-osdf-master-osdf-verify-python/453/",
        "patchset_number": 2
      },
      {
        "id": "dfb11a5d1fe9c26a64f2117ffa3f687744fe7c44",
        "author": {
          "account_id": 459,
          "name": "ONAP Jobbuilder",
          "display_name": null,
          "email": "onap-jobbuilder@jenkins.onap.org",
          "username": "onap-jobbuilder"
        },
        "author_role": "REVIEWER",
        "timestamp": "2020-04-30 11:13:29.000000000",
        "message": "Patch Set 2: Verified-1\n\nBuild Failed \n\nhttps://jenkins.onap.org/job/optf-osdf-master-osdf-verify-python/452/ : ABORTED\n\nNo problems were identified. If you know why this problem occurred, please add a suitable Cause for it. ( https://jenkins.onap.org/job/optf-osdf-master-osdf-verify-python/452/ )\n\nLogs: https://logs.onap.org/production/vex-yul-ecomp-jenkins-1/optf-osdf-master-osdf-verify-python/452",
        "patchset_number": 2
      },
      {
        "id": "686557b06fbaad9b6e2b93190b1b8374ef5fa381",
        "author": {
          "account_id": 459,
          "name": "ONAP Jobbuilder",
          "display_name": null,
          "email": "onap-jobbuilder@jenkins.onap.org",
          "username": "onap-jobbuilder"
        },
        "author_role": "REVIEWER",
        "timestamp": "2020-04-30 11:20:07.000000000",
        "message": "Patch Set 2: Verified+1\n\nBuild Successful \n\nhttps://jenkins.onap.org/job/optf-osdf-master-osdf-verify-python/453/ : SUCCESS\n\nLogs: https://logs.onap.org/production/vex-yul-ecomp-jenkins-1/optf-osdf-master-osdf-verify-python/453",
        "patchset_number": 2
      },
      {
        "id": "6383640419dc25197980aefa388048abbcd0084c",
        "author": {
          "account_id": 2671,
          "name": "krishna moorthy",
          "display_name": null,
          "email": "krishna981996@gmail.com",
          "username": "krishnaa96"
        },
        "author_role": "REVIEWER",
        "timestamp": "2020-04-30 13:41:01.000000000",
        "message": "Patch Set 2:\n\n(1 comment)",
        "patchset_number": 2
      },
      {
        "id": "703375aa1ce7b849b33ac9bee2400f51d1e35db1",
        "author": {
          "account_id": 2923,
          "name": "Vikas Varma",
          "display_name": null,
          "email": "vikas.varma@att.com",
          "username": "vrvarma"
        },
        "author_role": "REVIEWER",
        "timestamp": "2020-05-05 14:08:23.000000000",
        "message": "Patch Set 2: Code-Review+2",
        "patchset_number": 2
      },
      {
        "id": "fa52490532b6b5c371d9fda5068604cdd14bfec9",
        "author": {
          "account_id": 2923,
          "name": "Vikas Varma",
          "display_name": null,
          "email": "vikas.varma@att.com",
          "username": "vrvarma"
        },
        "author_role": "CI_BOT",
        "timestamp": "2020-05-05 14:08:34.000000000",
        "message": "Change has been successfully merged by Vikas Varma",
        "patchset_number": 2
      },
      {
        "id": "52230fd8d47eef6980238fdfce72482202fadf0d",
        "author": {
          "account_id": 459,
          "name": "ONAP Jobbuilder",
          "display_name": null,
          "email": "onap-jobbuilder@jenkins.onap.org",
          "username": "onap-jobbuilder"
        },
        "author_role": "REVIEWER",
        "timestamp": "2020-05-05 14:30:11.000000000",
        "message": "Patch Set 2:\n\nBuild Successful \n\nhttps://jenkins.onap.org/job/optf-osdf-master-osdf-merge-java/238/ : SUCCESS\n\nLogs: https://logs.onap.org/production/vex-yul-ecomp-jenkins-1/optf-osdf-master-osdf-merge-java/238",
        "patchset_number": 2
      }
    ]
  }
}